stable_audio_tools/__init__.py
stable_audio_tools/data/__init__.py
stable_audio_tools/data/dataset.py
stable_audio_tools/data/utils.py
stable_audio_tools/inference/__init__.py
stable_audio_tools/inference/generation.py
stable_audio_tools/inference/sampling.py
stable_audio_tools/inference/utils.py
stable_audio_tools/interface/__init__.py
stable_audio_tools/interface/aeiou.py
stable_audio_tools/interface/gradio.py
stable_audio_tools/interface/interfaces/__init__.py
stable_audio_tools/interface/interfaces/diffusion_cond.py
stable_audio_tools/models/__init__.py
stable_audio_tools/models/adp.py
stable_audio_tools/models/autoencoders.py
stable_audio_tools/models/blocks.py
stable_audio_tools/models/bottleneck.py
stable_audio_tools/models/codebook_patterns.py
stable_audio_tools/models/conditioners.py
stable_audio_tools/models/diffusion.py
stable_audio_tools/models/diffusion_prior.py
stable_audio_tools/models/discriminators.py
stable_audio_tools/models/dit.py
stable_audio_tools/models/encodec.py
stable_audio_tools/models/factory.py
stable_audio_tools/models/fsq.py
stable_audio_tools/models/lm.py
stable_audio_tools/models/lm_backbone.py
stable_audio_tools/models/local_attention.py
stable_audio_tools/models/pqmf.py
stable_audio_tools/models/pretrained.py
stable_audio_tools/models/pretransforms.py
stable_audio_tools/models/transformer.py
stable_audio_tools/models/utils.py
stable_audio_tools/models/wavelets.py
stable_audio_tools/training/__init__.py
stable_audio_tools/training/autoencoders.py
stable_audio_tools/training/diffusion.py
stable_audio_tools/training/factory.py
stable_audio_tools/training/lm.py
stable_audio_tools/training/utils.py
stable_audio_tools/training/losses/__init__.py
stable_audio_tools/training/losses/auraloss.py
stable_audio_tools/training/losses/losses.py
stable_audio_tools/training/losses/metrics.py
stable_audio_tools/training/losses/semantic.py
stable_audio_tools/training/losses/utils.py
stable_audio_tools-0.0.18.dist-info/LICENSE
stable_audio_tools-0.0.18.dist-info/METADATA
stable_audio_tools-0.0.18.dist-info/WHEEL
stable_audio_tools-0.0.18.dist-info/top_level.txt
stable_audio_tools-0.0.18.dist-info/RECORD
