Metadata-Version: 2.2
Name: stable-audio-tools
Version: 0.0.18
Summary: Training and inference tools for generative audio models from Stability AI
Home-page: https://github.com/Stability-AI/stable-audio-tools.git
Author: Stability AI
License-File: LICENSE
Requires-Dist: alias-free-torch==0.0.6
Requires-Dist: auraloss==0.4.0
Requires-Dist: descript-audio-codec==1.0.0
Requires-Dist: einops
Requires-Dist: einops-exts
Requires-Dist: ema-pytorch==0.2.3
Requires-Dist: encodec==0.1.1
Requires-Dist: gradio>=3.42.0
Requires-Dist: huggingface_hub
Requires-Dist: importlib-resources==5.12.0
Requires-Dist: k-diffusion==0.1.1
Requires-Dist: laion-clap==1.1.4
Requires-Dist: local-attention==1.8.6
Requires-Dist: pandas==2.0.2
Requires-Dist: prefigure==0.0.9
Requires-Dist: pytorch_lightning==2.1.0
Requires-Dist: PyWavelets==1.4.1
Requires-Dist: safetensors
Requires-Dist: sentencepiece==0.1.99
Requires-Dist: torch>=2.0.1
Requires-Dist: torchaudio>=2.0.2
Requires-Dist: torchmetrics==0.11.4
Requires-Dist: tqdm
Requires-Dist: transformers
Requires-Dist: v-diffusion-pytorch==0.0.2
Requires-Dist: vector-quantize-pytorch==1.14.41
Requires-Dist: wandb==0.15.4
Requires-Dist: webdataset==0.2.100
Requires-Dist: x-transformers<1.27.0
Dynamic: author
Dynamic: home-page
Dynamic: requires-dist
Dynamic: summary
